ua_generator/__init__.py
ua_generator/client_hints.py
ua_generator/headers.py
ua_generator/navigator.py
ua_generator/options.py
ua_generator/py.typed
ua_generator/serialization.py
ua_generator/user_agent.py
ua_generator/utils.py
ua_generator/data/__init__.py
ua_generator/data/filterer.py
ua_generator/data/generator.py
ua_generator/data/version.py
ua_generator/data/browsers/__init__.py
ua_generator/data/browsers/chrome.py
ua_generator/data/browsers/edge.py
ua_generator/data/browsers/firefox.py
ua_generator/data/browsers/safari.py
ua_generator/data/platforms/__init__.py
ua_generator/data/platforms/ios.py
ua_generator/data/platforms/linux.py
ua_generator/data/platforms/macos.py
ua_generator/data/platforms/windows.py
ua_generator/data/platforms/android/__init__.py
ua_generator/data/platforms/android/android_oppo.py
ua_generator/data/platforms/android/android_pixel.py
ua_generator/data/platforms/android/android_samsung.py
ua_generator/data/platforms/android/android_xiaomi.py
ua_generator-2.0.19.dist-info/licenses/LICENSE
ua_generator-2.0.19.dist-info/METADATA
ua_generator-2.0.19.dist-info/WHEEL
ua_generator-2.0.19.dist-info/top_level.txt
ua_generator-2.0.19.dist-info/RECORD
