Metadata-Version: 2.4
Name: ua-generator
Version: 2.0.19
Summary: A random user-agent generator
Home-page: https://github.com/iamdual/ua-generator
Author: Ekin Karadeniz
Author-email: iamdual@icloud.com
Project-URL: Bug Tracker, https://github.com/iamdual/ua-generator/issues
Classifier: Topic :: Internet :: WWW/HTTP
Classifier: Programming Language :: Python :: 3
Classifier: License :: OSI Approved :: Apache Software License
Classifier: Operating System :: OS Independent
Requires-Python: >=3.9
License-File: LICENSE
Dynamic: license-file
